flamechess/MCTS.py
flamechess/__init__.py
flamechess/jiuqi.py
flamechess/luqi.py
flamechess/luqi_player.py
flamechess/play.py
flamechess/socketIO.py
flamechess/zhuobie.py
flamechess/zhuobie_player.py
flamechess-0.3.1.dist-info/LICENSE
flamechess-0.3.1.dist-info/METADATA
flamechess-0.3.1.dist-info/WHEEL
flamechess-0.3.1.dist-info/top_level.txt
flamechess-0.3.1.dist-info/RECORD
