Metadata-Version: 2.1
Name: flamechess
Version: 0.3.1
Summary: Flamechess Tools
Home-page: https://github.com/zhc7/flamechess-package
Author: ZHC 张瀚宸
Author-email: bjhansen2012@outlook.com
License: UNKNOWN
Platform: UNKNOWN
Classifier: Environment :: Console
Classifier: Programming Language :: Python :: 3.8
Classifier: License :: OSI Approved :: GNU General Public License v3 (GPLv3)
Classifier: Programming Language :: Python :: 3
Requires-Python: >=3.5.0
Requires-Dist: requests
Requires-Dist: chessterm-sdk
Requires-Dist: python-socketio[client]
